README.rst
setup.py
mysqlbinlog2blinker/__init__.py
mysqlbinlog2blinker/_subscribers.py
mysqlbinlog2blinker/binlog_pos_memory.py
mysqlbinlog2blinker/metadata.py
mysqlbinlog2blinker/signals.py
mysqlbinlog2blinker.egg-info/PKG-INFO
mysqlbinlog2blinker.egg-info/SOURCES.txt
mysqlbinlog2blinker.egg-info/dependency_links.txt
mysqlbinlog2blinker.egg-info/entry_points.txt
mysqlbinlog2blinker.egg-info/not-zip-safe
mysqlbinlog2blinker.egg-info/requires.txt
mysqlbinlog2blinker.egg-info/top_level.txt