Metadata-Version: 1.1
Name: mysqlbinlog2blinker
Version: 0.1
Summary: This project listen on mysql binlog (as a slave) and send the binlog event to blinker signal. It can remember last binlog position and work as a MySQL slave.
Home-page: https://github.com/tarzanjw/python-mysql-binlog-to-blinker
Author: Tarzan
Author-email: hoc3010@gmail.com
License: UNKNOWN
Platform: UNKNOWN
Classifier: Intended Audience :: Developers
Classifier: License :: OSI Approved :: MIT License
Classifier: Natural Language :: English
Classifier: Operating System :: OS Independent
Classifier: Programming Language :: Python :: 2.7
Classifier: Programming Language :: Python :: 3.3
Classifier: Programming Language :: Python :: Implementation :: PyPy
Classifier: Topic :: Documentation
Classifier: Topic :: Software Development :: Libraries :: Python Modules
Classifier: Topic :: System :: Installation/Setup
Classifier: Topic :: System :: Software Distribution
